pdLDS/__init__.py
pdLDS/cDynamics.py
pdLDS/dynamics.py
pdLDS/generate.py
pdLDS/likelihood.py
pdLDS/offset.py
pdLDS/pdLDS.py
pdLDS/utils.py
pdLDS-0.12.dist-info/LICENSE
pdLDS-0.12.dist-info/METADATA
pdLDS-0.12.dist-info/WHEEL
pdLDS-0.12.dist-info/top_level.txt
pdLDS-0.12.dist-info/RECORD
