Metadata-Version: 2.1
Name: pdLDS
Version: 0.12
Summary: Probabilistic Decomposed Linear Dynamical Systems
Author: Yenho Chen
Author-email: <yenho@gatech.edu>
Keywords: python,dynamical systems
Classifier: Intended Audience :: Developers
Classifier: Programming Language :: Python :: 3
Classifier: Operating System :: Unix
Classifier: Operating System :: MacOS :: MacOS X
Classifier: Operating System :: Microsoft :: Windows
License-File: LICENSE
Requires-Dist: tqdm
Requires-Dist: numpy
Requires-Dist: numba
Requires-Dist: torch
Requires-Dist: scipy
